file_uploader/__init__.py
file_uploader/__main__.py
file_uploader/constants.py
file_uploader/exceptions.py
file_uploader/jobs/__init__.py
file_uploader/jobs/db_manager.py
file_uploader/metadata/__init__.py
file_uploader/metadata/db_interface.py
file_uploader/setup.py
file_uploader/src/__init__.py
file_uploader/src/file_upload.py
file_uploader/src/storage_handler.py
file_uploader/tests/__init__.py
file_uploader/tests/test_jobs.py
file_uploader/tests/test_metadata.py
file_uploader/tests/test_uploader.py
file_uploader/uploader.py
file_uploader/utils/__init__.py
file_uploader/utils/date_utils.py
pyspfileuploader-1.0.13.dist-info/entry_points.txt
pyspfileuploader-1.0.13.dist-info/METADATA
pyspfileuploader-1.0.13.dist-info/WHEEL
pyspfileuploader-1.0.13.dist-info/RECORD
