Metadata-Version: 2.3
Name: pyspfileuploader
Version: 1.0.13
Summary: A versatile Python package for uploading files to multiple storage backends including local, S3, Azure ADLS, and Blob storage. Supports ZIP file extraction and multiple file uploads including reading files.
License: MIT
Author: Deepak Gadge
Author-email: dip.gadge2008@hotmail.com
Requires-Python: >=3.9,<4.0
Classifier: License :: OSI Approved :: MIT License
Classifier: Programming Language :: Python :: 3
Classifier: Programming Language :: Python :: 3.9
Classifier: Programming Language :: Python :: 3.10
Classifier: Programming Language :: Python :: 3.11
Classifier: Programming Language :: Python :: 3.12
Classifier: Programming Language :: Python :: 3.13
Requires-Dist: azure-storage-blob (>=12.17.0,<13.0.0)
Requires-Dist: azure-storage-file-datalake (>=12.11.0,<13.0.0)
Requires-Dist: boto3 (>=1.28.1,<2.0.0)
Requires-Dist: databricks-sdk (>=0.1.0,<0.2.0)
Requires-Dist: google-cloud-storage (>=2.10.0,<3.0.0)
Requires-Dist: pandas (>=2.0.3,<3.0.0)
Requires-Dist: python-dotenv (>=1.0.0,<2.0.0)
